LICENSE
fakevalkey/__init__.py
fakevalkey/_basefakesocket.py
fakevalkey/_command_args_parsing.py
fakevalkey/_commands.py
fakevalkey/_connection.py
fakevalkey/_fakesocket.py
fakevalkey/_helpers.py
fakevalkey/_msgs.py
fakevalkey/_server.py
fakevalkey/_stream.py
fakevalkey/_zset.py
fakevalkey/aioredis.py
fakevalkey/commands.json
fakevalkey/commands_mixins/__init__.py
fakevalkey/commands_mixins/bitmap_mixin.py
fakevalkey/commands_mixins/connection_mixin.py
fakevalkey/commands_mixins/generic_mixin.py
fakevalkey/commands_mixins/geo_mixin.py
fakevalkey/commands_mixins/hash_mixin.py
fakevalkey/commands_mixins/list_mixin.py
fakevalkey/commands_mixins/pubsub_mixin.py
fakevalkey/commands_mixins/scripting_mixin.py
fakevalkey/commands_mixins/server_mixin.py
fakevalkey/commands_mixins/set_mixin.py
fakevalkey/commands_mixins/sortedset_mixin.py
fakevalkey/commands_mixins/streams_mixin.py
fakevalkey/commands_mixins/string_mixin.py
fakevalkey/commands_mixins/transactions_mixin.py
fakevalkey/geo/__init__.py
fakevalkey/geo/geohash.py
fakevalkey/geo/haversine.py
fakevalkey/py.typed
fakevalkey/stack/__init__.py
fakevalkey/stack/_bf_mixin.py
fakevalkey/stack/_cf_mixin.py
fakevalkey/stack/_cms_mixin.py
fakevalkey/stack/_json_mixin.py
fakevalkey/stack/_tdigest_mixin.py
fakevalkey/stack/_timeseries_mixin.py
fakevalkey/stack/_timeseries_model.py
fakevalkey/stack/_topk_mixin.py
fakevalkey-0.0.1.dist-info/LICENSE
fakevalkey-0.0.1.dist-info/METADATA
fakevalkey-0.0.1.dist-info/WHEEL
fakevalkey-0.0.1.dist-info/RECORD
